{
    "schemaVersion": 1,
    "id": "vectorial",
    "version": "${version}",
    "name": "Vectorial",
    "description": "Bytecode-level SoA entity field layout enabling SIMD batch queries. Transparent — no API changes, 49 Entity fields mapped to contiguous double[] arrays via Javassist + ByteBuddy agent.",
    "authors": ["uright008"],
    "license": "MIT",
    "environment": "server",
    "entrypoints": {
        "preLaunch": ["com.github.uright008.vec.VectorialFabric"]
    },
    "mixins": ["vectorial.mixins.json"],
    "depends": {
        "fabricloader": ">=0.19.2",
        "minecraft": "~26.2",
        "java": ">=25",
        "fabric-api": "*"
    }
}
